[
  {
    "input_path": "ocr_table_output\\pages\\page_005.png",
    "page_index": null,
    "page_count": null,
    "width": 1826,
    "height": 2574,
    "doc_preprocessor_res": {
      "input_path": null,
      "page_index": null,
      "input_img": "[[[255 ... 255]\n  ...\n  [255 ... 255]]\n\n ...\n\n [[255 ... 255]\n  ...\n  [255 ... 255]]]",
      "model_settings": {
        "use_doc_orientation_classify": true,
        "use_doc_unwarping": true
      },
      "angle": 180,
      "rot_img": "[[[  0 ...   0]\n  ...\n  [  0 ...   0]]\n\n ...\n\n [[  0 ...   0]\n  ...\n  [255 ... 255]]]",
      "output_img": "[[[255 ... 255]\n  ...\n  [255 ... 255]]\n\n ...\n\n [[255 ... 255]\n  ...\n  [255 ... 255]]]"
    },
    "layout_det_res": {
      "input_path": null,
      "page_index": null,
      "input_img": "[[[255 ... 255]\n  ...\n  [255 ... 255]]\n\n ...\n\n [[255 ... 255]\n  ...\n  [255 ... 255]]]",
      "boxes": [
        {
          "cls_id": 8,
          "label": "table",
          "score": 0.9866393804550171,
          "coordinate": [
            "131.83173",
            "0.3166504",
            "1741.9302",
            "2570.3894"
          ]
        }
      ]
    },
    "region_det_res": {
      "input_path": null,
      "page_index": null,
      "input_img": "[[[255 ... 255]\n  ...\n  [255 ... 255]]\n\n ...\n\n [[255 ... 255]\n  ...\n  [255 ... 255]]]",
      "boxes": [
        {
          "cls_id": 0,
          "label": "Region",
          "score": 0.9412157535552979,
          "coordinate": "[ 131.83173 ... 2570.3894 ]"
        }
      ]
    },
    "overall_ocr_res": {
      "input_path": null,
      "page_index": null,
      "doc_preprocessor_res": {
        "output_img": "[[[255 ... 255]\n  ...\n  [255 ... 255]]\n\n ...\n\n [[255 ... 255]\n  ...\n  [255 ... 255]]]"
      },
      "dt_polys": [
        "[[262  12]\n ...\n [263  54]]",
        "[[1307    4]\n ...\n [1308   42]]",
        "[[264  64]\n ...\n [265 101]]",
        "[[1389   55]\n ...\n [1390   93]]",
        "[[1307   94]\n ...\n [1308  132]]",
        "[[268 105]\n ...\n [269 140]]",
        "[[1418  136]\n ...\n [1418  174]]",
        "[[268 147]\n ...\n [269 185]]",
        "[[1305  176]\n ...\n [1306  217]]",
        "[[271 189]\n ...\n [272 224]]",
        "[[1334  223]\n ...\n [1335  265]]",
        "[[225 238]\n ...\n [226 273]]",
        "[[1350  274]\n ...\n [1351  309]]",
        "[[273 287]\n ...\n [274 318]]",
        "[[1287  313]\n ...\n [1288  347]]",
        "[[273 326]\n ...\n [274 360]]",
        "[[1307  350]\n ...\n [1308  385]]",
        "[[272 364]\n ...\n [273 398]]",
        "[[1388  399]\n ...\n [1389  435]]",
        "[[273 411]\n ...\n [274 446]]",
        "[[1346  435]\n ...\n [1347  475]]",
        "[[273 452]\n ...\n [273 486]]",
        "[[1416  483]\n ...\n [1417  521]]",
        "[[271 497]\n ...\n [272 534]]",
        "[[1347  524]\n ...\n [1348  561]]",
        "[[271 538]\n ...\n [271 573]]",
        "[[224 584]\n ...\n [223 616]]",
        "[[1380  609]\n ...\n [1381  651]]",
        "[[224 623]\n ...\n [224 659]]",
        "[[224 670]\n ...\n [223 706]]",
        "[[1318  697]\n ...\n [1319  735]]",
        "[[225 710]\n ...\n [225 744]]",
        "[[1335  738]\n ...\n [1336  775]]",
        "[[1527  733]\n ...\n [1526  769]]",
        "[[224 744]\n ...\n [224 785]]",
        "[[1463  785]\n ...\n [1464  821]]",
        "[[1384  823]\n ...\n [1385  858]]",
        "[[1293  867]\n ...\n [1294  902]]",
        "[[274 879]\n ...\n [275 910]]",
        "[[659 907]\n ...\n [659 945]]",
        "[[955 903]\n ...\n [955 945]]",
        "[[1312  902]\n ...\n [1313  939]]",
        "[[273 915]\n ...\n [274 949]]",
        "[[1483  950]\n ...\n [1484  986]]",
        "[[1377  989]\n ...\n [1378 1026]]",
        "[[ 960 1033]\n ...\n [ 960 1071]]",
        "[[1383 1026]\n ...\n [1383 1061]]",
        "[[ 275 1041]\n ...\n [ 276 1075]]",
        "[[ 661 1037]\n ...\n [ 661 1070]]",
        "[[1282 1078]\n ...\n [1283 1112]]",
        "[[ 958 1117]\n ...\n [ 958 1156]]",
        "[[1382 1110]\n ...\n [1383 1148]]",
        "[[ 274 1123]\n ...\n [ 274 1160]]",
        "[[ 661 1122]\n ...\n [ 661 1156]]",
        "[[1510 1160]\n ...\n [1510 1191]]",
        "[[1419 1195]\n ...\n [1419 1234]]",
        "[[ 225 1213]\n ...\n [ 225 1249]]",
        "[[1488 1248]\n ...\n [1489 1283]]",
        "[[ 274 1259]\n ...\n [ 275 1294]]",
        "[[ 660 1294]\n ...\n [ 661 1331]]",
        "[[ 958 1291]\n ...\n [ 958 1330]]",
        "[[1270 1286]\n ...\n [1271 1326]]",
        "[[ 275 1299]\n ...\n [ 276 1332]]",
        "[[1518 1326]\n ...\n [1517 1367]]",
        "[[ 272 1340]\n ...\n [ 272 1380]]",
        "[[ 661 1381]\n ...\n [ 662 1417]]",
        "[[ 958 1375]\n ...\n [ 958 1415]]",
        "[[1270 1372]\n ...\n [1271 1413]]",
        "[[ 274 1383]\n ...\n [ 275 1417]]",
        "[[1389 1418]\n ...\n [1390 1460]]",
        "[[ 227 1430]\n ...\n [ 228 1467]]",
        "[[1347 1467]\n ...\n [1348 1504]]",
        "[[ 275 1478]\n ...\n [ 276 1511]]",
        "[[ 275 1510]\n ...\n [ 275 1545]]",
        "[[1297 1507]\n ...\n [1298 1543]]",
        "[[ 275 1551]\n ...\n [ 275 1586]]",
        "[[ 661 1548]\n ...\n [ 661 1587]]",
        "[[ 960 1543]\n ...\n [ 960 1589]]",
        "[[1316 1543]\n ...\n [1317 1582]]",
        "[[ 275 1597]\n ...\n [ 275 1632]]",
        "[[1402 1595]\n ...\n [1403 1630]]",
        "[[ 275 1638]\n ...\n [ 276 1672]]",
        "[[ 662 1634]\n ...\n [ 662 1672]]",
        "[[ 960 1631]\n ...\n [ 960 1673]]",
        "[[1335 1631]\n ...\n [1336 1669]]",
        "[[ 275 1680]\n ...\n [ 275 1718]]",
        "[[1431 1676]\n ...\n [1432 1715]]",
        "[[ 276 1722]\n ...\n [ 277 1757]]",
        "[[ 662 1721]\n ...\n [ 662 1757]]",
        "[[ 961 1717]\n ...\n [ 961 1757]]",
        "[[1336 1717]\n ...\n [1337 1755]]",
        "[[ 228 1769]\n ...\n [ 229 1803]]",
        "[[1368 1761]\n ...\n [1369 1801]]",
        "[[1383 1810]\n ...\n [1384 1845]]",
        "[[ 276 1854]\n ...\n [ 276 1885]]",
        "[[1349 1851]\n ...\n [1350 1885]]",
        "[[ 275 1891]\n ...\n [ 275 1922]]",
        "[[1298 1889]\n ...\n [1299 1924]]",
        "[[ 275 1929]\n ...\n [ 275 1961]]",
        "[[ 664 1926]\n ...\n [ 664 1965]]",
        "[[ 962 1922]\n ...\n [ 962 1966]]",
        "[[1317 1927]\n ...\n [1318 1962]]",
        "[[ 272 1973]\n ...\n [ 273 2009]]",
        "[[1491 1974]\n ...\n [1492 2009]]",
        "[[ 274 2016]\n ...\n [ 274 2046]]",
        "[[1294 2013]\n ...\n [1295 2050]]",
        "[[ 274 2052]\n ...\n [ 273 2083]]",
        "[[ 661 2052]\n ...\n [ 661 2087]]",
        "[[ 961 2051]\n ...\n [ 961 2089]]",
        "[[1340 2052]\n ...\n [1341 2087]]",
        "[[1518 2090]\n ...\n [1516 2132]]",
        "[[ 275 2134]\n ...\n [ 274 2166]]",
        "[[1296 2138]\n ...\n [1297 2175]]",
        "[[ 273 2174]\n ...\n [ 272 2206]]",
        "[[ 660 2178]\n ...\n [ 660 2217]]",
        "[[ 959 2178]\n ...\n [ 959 2220]]",
        "[[1340 2178]\n ...\n [1341 2213]]",
        "[[1413 2221]\n ...\n [1414 2260]]",
        "[[ 225 2257]\n ...\n [ 224 2292]]",
        "[[1373 2264]\n ...\n [1374 2302]]",
        "[[ 224 2305]\n ...\n [ 223 2338]]",
        "[[1386 2313]\n ...\n [1387 2351]]",
        "[[ 222 2341]\n ...\n [ 221 2379]]",
        "[[ 656 2355]\n ...\n [ 655 2394]]",
        "[[ 956 2354]\n ...\n [ 956 2397]]",
        "[[1303 2350]\n ...\n [1304 2391]]",
        "[[ 224 2390]\n ...\n [ 223 2421]]",
        "[[1302 2401]\n ...\n [1303 2438]]",
        "[[ 220 2420]\n ...\n [ 219 2460]]",
        "[[1281 2434]\n ...\n [1282 2475]]",
        "[[1366 2480]\n ...\n [1368 2521]]",
        "[[ 267 2508]\n ...\n [ 265 2547]]",
        "[[1386 2517]\n ...\n [1387 2562]]"
      ],
      "model_settings": {
        "use_doc_preprocessor": false,
        "use_textline_orientation": true
      },
      "text_det_params": {
        "limit_side_len": 736,
        "limit_type": "min",
        "thresh": 0.3,
        "max_side_limit": 4000,
        "box_thresh": 0.6,
        "unclip_ratio": 1.5
      },
      "text_type": "general",
      "text_rec_score_thresh": 0.0,
      "return_word_box": false,
      "rec_texts": [
        "Allowance for impairment",
        "Cadangan kerugian",
        "related parties",
        "pihak berelasi",
        "Piutang murabahah",
        "Murabahah receivables",
        "pihak ketiga",
        "third parties",
        "Piutang murabahah",
        "Murabahah receivables",
        "Piutang murabahah",
        "Murabahah receivables",
        "piutang nasabah",
        "from customers",
        "penurunan nilai pada",
        "losses for receivables",
        "Cadangan kerugian",
        "Allowance for impairment",
        "pihak berelasi",
        "customers related parties",
        "Piutang nasabah",
        "Receivables from",
        "pihak ketiga",
        "customers third parties",
        "Piutang nasabah",
        "Receivables from",
        "customers",
        "Piutang nasabah",
        "Receivables from",
        "institution",
        "kliring dan penjaminan",
        "and settlement guarantee",
        "dari lembaga",
        "Piutang",
        "Receivables from clearing",
        "diberikan",
        "pinjaman yang",
        "penurunan nilai pada",
        "losses for loans",
        "( 38,684,520 )",
        "( 35,860,626 )",
        "Cadangan kerugian",
        "Allowance for impairment",
        "berelasi",
        "diberikan pihak",
        "239,016,801",
        "Pinjaman yang",
        "Loans related parties",
        "159,402,689",
        "diberikan pihak ketiga",
        "660,513,890",
        "Pinjaman yang",
        "Loans third parties",
        "616,469,089",
        "diberikan",
        "Pinjaman yang",
        "Loans",
        "berelasi",
        "related parties",
        "341,832",
        "768,083",
        "Tagihan derivatif pihak",
        "Derivative receivables",
        "ketiga",
        "third parties",
        "1,451,146",
        "4,654,266",
        "Tagihan derivatif pihak",
        "Derivative receivables",
        "Tagihan derivatif",
        "Derivative receivables",
        "tagihan akseptasi",
        "receivables",
        "losses for acceptance",
        "penurunan nilai pada",
        "Allowance for impairment",
        "(93,249 )",
        "( 133,986 )",
        "Cadangan kerugian",
        "related parties",
        "pihak berelasi",
        "Acceptance receivables",
        "2,825,260",
        "6,053,827",
        "Tagihan akseptasi",
        "third parties",
        "pihak ketiga",
        "Acceptance receivables",
        "13,193,510",
        "13,528,919",
        "Tagihan akseptasi",
        "Acceptance receivables",
        "Tagihan akseptasi",
        "tagihan lainnya",
        "receivables",
        "wesel ekspor dan",
        "losses for bills and other",
        "penurunan nilai pada",
        "Allowance for impairment",
        "( 52,828 )",
        "( 67,962 )",
        "Cadangan kerugian",
        "parties",
        "berelasi",
        "receivables related",
        "tagihan lainnya pihak",
        "Bills and other",
        "6,208,736",
        "5,338,937",
        "Wesel ekspor dan",
        "ketiga",
        "receivables third parties",
        "tagihan lainnya pihak",
        "Bills and other",
        "7,087,118",
        "8,181,871",
        "Wesel ekspor dan",
        "tagihan lainnya",
        "Bills and other receivables",
        "Wesel ekspor dan",
        "agreement to resale",
        "janji dijual kembali",
        "Securities purchased under",
        "7,971,923",
        "6,910,606",
        "Efek yang dibeli dengan",
        "in unit-linked contracts",
        "pada kontrak unit-linked",
        "Investments of policyholder",
        "Investasi pemegang polis",
        "diperdagangkan",
        "securities",
        "efek-efek yang"
      ],
      "rec_scores": [
        0.9754554629325867,
        0.9944132566452026,
        0.9978402256965637,
        0.9941468238830566,
        0.9990127682685852,
        0.994726836681366,
        0.9903363585472107,
        0.9983381032943726,
        0.9978089928627014,
        0.9966235160827637,
        0.9768498539924622,
        0.9993922114372253,
        0.9814630150794983,
        0.9945217370986938,
        0.9715840220451355,
        0.9905992150306702,
        0.9808650016784668,
        0.9916439056396484,
        0.9714239835739136,
        0.9948005080223083,
        0.998302698135376,
        0.9979040026664734,
        0.9649441838264465,
        0.9726781249046326,
        0.9812729358673096,
        0.9972711801528931,
        0.999771773815155,
        0.9664971828460693,
        0.9715057611465454,
        0.9995871186256409,
        0.9975797533988953,
        0.9855162501335144,
        0.9911242127418518,
        0.9981240630149841,
        0.997901439666748,
        0.9994649887084961,
        0.9962438941001892,
        0.9866554141044617,
        0.9778344631195068,
        0.9579394459724426,
        0.9471908211708069,
        0.9904776215553284,
        0.9730876088142395,
        0.9997009038925171,
        0.9971403479576111,
        0.9963549971580505,
        0.9975780248641968,
        0.9887065887451172,
        0.9965362548828125,
        0.9970912933349609,
        0.9908624887466431,
        0.9968586564064026,
        0.982305109500885,
        0.9953563213348389,
        0.9997482299804688,
        0.9976640343666077,
        0.9989210963249207,
        0.9996323585510254,
        0.9979419708251953,
        0.9962605834007263,
        0.9943564534187317,
        0.9973506331443787,
        0.9878824353218079,
        0.998356819152832,
        0.9969338774681091,
        0.9964568614959717,
        0.9920201897621155,
        0.995993435382843,
        0.9989253878593445,
        0.9760101437568665,
        0.9846164584159851,
        0.9822039008140564,
        0.999752402305603,
        0.9905247688293457,
        0.9919639825820923,
        0.9702425599098206,
        0.9740949273109436,
        0.9344154000282288,
        0.9914209842681885,
        0.9986578226089478,
        0.9874114990234375,
        0.9985845685005188,
        0.9914494752883911,
        0.9891331195831299,
        0.9935309290885925,
        0.9972193241119385,
        0.9888746738433838,
        0.9989120364189148,
        0.9905449748039246,
        0.9924635887145996,
        0.994156002998352,
        0.9898025989532471,
        0.9995492100715637,
        0.9873286485671997,
        0.9996118545532227,
        0.9839194416999817,
        0.9721908569335938,
        0.9969719648361206,
        0.9593393206596375,
        0.9417871236801147,
        0.9073601961135864,
        0.9881921410560608,
        0.9990367889404297,
        0.9995502829551697,
        0.9973098635673523,
        0.9968988299369812,
        0.9803093075752258,
        0.9965012669563293,
        0.9925707578659058,
        0.9979304671287537,
        0.9993619322776794,
        0.9770371913909912,
        0.9976240992546082,
        0.9761030673980713,
        0.9986343383789062,
        0.9938298463821411,
        0.9991271495819092,
        0.9978638291358948,
        0.9965037107467651,
        0.9946194887161255,
        0.9802356362342834,
        0.9949008822441101,
        0.9986130595207214,
        0.9990517497062683,
        0.9967261552810669,
        0.9934276342391968,
        0.9773322939872742,
        0.9947546124458313,
        0.9972293972969055,
        0.9760095477104187,
        0.9995673894882202,
        0.9993492960929871,
        0.9898203015327454
      ],
      "rec_polys": [
        "[[262  12]\n ...\n [263  54]]",
        "[[1307    4]\n ...\n [1308   42]]",
        "[[264  64]\n ...\n [265 101]]",
        "[[1389   55]\n ...\n [1390   93]]",
        "[[1307   94]\n ...\n [1308  132]]",
        "[[268 105]\n ...\n [269 140]]",
        "[[1418  136]\n ...\n [1418  174]]",
        "[[268 147]\n ...\n [269 185]]",
        "[[1305  176]\n ...\n [1306  217]]",
        "[[271 189]\n ...\n [272 224]]",
        "[[1334  223]\n ...\n [1335  265]]",
        "[[225 238]\n ...\n [226 273]]",
        "[[1350  274]\n ...\n [1351  309]]",
        "[[273 287]\n ...\n [274 318]]",
        "[[1287  313]\n ...\n [1288  347]]",
        "[[273 326]\n ...\n [274 360]]",
        "[[1307  350]\n ...\n [1308  385]]",
        "[[272 364]\n ...\n [273 398]]",
        "[[1388  399]\n ...\n [1389  435]]",
        "[[273 411]\n ...\n [274 446]]",
        "[[1346  435]\n ...\n [1347  475]]",
        "[[273 452]\n ...\n [273 486]]",
        "[[1416  483]\n ...\n [1417  521]]",
        "[[271 497]\n ...\n [272 534]]",
        "[[1347  524]\n ...\n [1348  561]]",
        "[[271 538]\n ...\n [271 573]]",
        "[[224 584]\n ...\n [223 616]]",
        "[[1380  609]\n ...\n [1381  651]]",
        "[[224 623]\n ...\n [224 659]]",
        "[[224 670]\n ...\n [223 706]]",
        "[[1318  697]\n ...\n [1319  735]]",
        "[[225 710]\n ...\n [225 744]]",
        "[[1335  738]\n ...\n [1336  775]]",
        "[[1527  733]\n ...\n [1526  769]]",
        "[[224 744]\n ...\n [224 785]]",
        "[[1463  785]\n ...\n [1464  821]]",
        "[[1384  823]\n ...\n [1385  858]]",
        "[[1293  867]\n ...\n [1294  902]]",
        "[[274 879]\n ...\n [275 910]]",
        "[[659 907]\n ...\n [659 945]]",
        "[[955 903]\n ...\n [955 945]]",
        "[[1312  902]\n ...\n [1313  939]]",
        "[[273 915]\n ...\n [274 949]]",
        "[[1483  950]\n ...\n [1484  986]]",
        "[[1377  989]\n ...\n [1378 1026]]",
        "[[ 960 1033]\n ...\n [ 960 1071]]",
        "[[1383 1026]\n ...\n [1383 1061]]",
        "[[ 275 1041]\n ...\n [ 276 1075]]",
        "[[ 661 1037]\n ...\n [ 661 1070]]",
        "[[1282 1078]\n ...\n [1283 1112]]",
        "[[ 958 1117]\n ...\n [ 958 1156]]",
        "[[1382 1110]\n ...\n [1383 1148]]",
        "[[ 274 1123]\n ...\n [ 274 1160]]",
        "[[ 661 1122]\n ...\n [ 661 1156]]",
        "[[1510 1160]\n ...\n [1510 1191]]",
        "[[1419 1195]\n ...\n [1419 1234]]",
        "[[ 225 1213]\n ...\n [ 225 1249]]",
        "[[1488 1248]\n ...\n [1489 1283]]",
        "[[ 274 1259]\n ...\n [ 275 1294]]",
        "[[ 660 1294]\n ...\n [ 661 1331]]",
        "[[ 958 1291]\n ...\n [ 958 1330]]",
        "[[1270 1286]\n ...\n [1271 1326]]",
        "[[ 275 1299]\n ...\n [ 276 1332]]",
        "[[1518 1326]\n ...\n [1517 1367]]",
        "[[ 272 1340]\n ...\n [ 272 1380]]",
        "[[ 661 1381]\n ...\n [ 662 1417]]",
        "[[ 958 1375]\n ...\n [ 958 1415]]",
        "[[1270 1372]\n ...\n [1271 1413]]",
        "[[ 274 1383]\n ...\n [ 275 1417]]",
        "[[1389 1418]\n ...\n [1390 1460]]",
        "[[ 227 1430]\n ...\n [ 228 1467]]",
        "[[1347 1467]\n ...\n [1348 1504]]",
        "[[ 275 1478]\n ...\n [ 276 1511]]",
        "[[ 275 1510]\n ...\n [ 275 1545]]",
        "[[1297 1507]\n ...\n [1298 1543]]",
        "[[ 275 1551]\n ...\n [ 275 1586]]",
        "[[ 661 1548]\n ...\n [ 661 1587]]",
        "[[ 960 1543]\n ...\n [ 960 1589]]",
        "[[1316 1543]\n ...\n [1317 1582]]",
        "[[ 275 1597]\n ...\n [ 275 1632]]",
        "[[1402 1595]\n ...\n [1403 1630]]",
        "[[ 275 1638]\n ...\n [ 276 1672]]",
        "[[ 662 1634]\n ...\n [ 662 1672]]",
        "[[ 960 1631]\n ...\n [ 960 1673]]",
        "[[1335 1631]\n ...\n [1336 1669]]",
        "[[ 275 1680]\n ...\n [ 275 1718]]",
        "[[1431 1676]\n ...\n [1432 1715]]",
        "[[ 276 1722]\n ...\n [ 277 1757]]",
        "[[ 662 1721]\n ...\n [ 662 1757]]",
        "[[ 961 1717]\n ...\n [ 961 1757]]",
        "[[1336 1717]\n ...\n [1337 1755]]",
        "[[ 228 1769]\n ...\n [ 229 1803]]",
        "[[1368 1761]\n ...\n [1369 1801]]",
        "[[1383 1810]\n ...\n [1384 1845]]",
        "[[ 276 1854]\n ...\n [ 276 1885]]",
        "[[1349 1851]\n ...\n [1350 1885]]",
        "[[ 275 1891]\n ...\n [ 275 1922]]",
        "[[1298 1889]\n ...\n [1299 1924]]",
        "[[ 275 1929]\n ...\n [ 275 1961]]",
        "[[ 664 1926]\n ...\n [ 664 1965]]",
        "[[ 962 1922]\n ...\n [ 962 1966]]",
        "[[1317 1927]\n ...\n [1318 1962]]",
        "[[ 272 1973]\n ...\n [ 273 2009]]",
        "[[1491 1974]\n ...\n [1492 2009]]",
        "[[ 274 2016]\n ...\n [ 274 2046]]",
        "[[1294 2013]\n ...\n [1295 2050]]",
        "[[ 274 2052]\n ...\n [ 273 2083]]",
        "[[ 661 2052]\n ...\n [ 661 2087]]",
        "[[ 961 2051]\n ...\n [ 961 2089]]",
        "[[1340 2052]\n ...\n [1341 2087]]",
        "[[1518 2090]\n ...\n [1516 2132]]",
        "[[ 275 2134]\n ...\n [ 274 2166]]",
        "[[1296 2138]\n ...\n [1297 2175]]",
        "[[ 273 2174]\n ...\n [ 272 2206]]",
        "[[ 660 2178]\n ...\n [ 660 2217]]",
        "[[ 959 2178]\n ...\n [ 959 2220]]",
        "[[1340 2178]\n ...\n [1341 2213]]",
        "[[1413 2221]\n ...\n [1414 2260]]",
        "[[ 225 2257]\n ...\n [ 224 2292]]",
        "[[1373 2264]\n ...\n [1374 2302]]",
        "[[ 224 2305]\n ...\n [ 223 2338]]",
        "[[1386 2313]\n ...\n [1387 2351]]",
        "[[ 222 2341]\n ...\n [ 221 2379]]",
        "[[ 656 2355]\n ...\n [ 655 2394]]",
        "[[ 956 2354]\n ...\n [ 956 2397]]",
        "[[1303 2350]\n ...\n [1304 2391]]",
        "[[ 224 2390]\n ...\n [ 223 2421]]",
        "[[1302 2401]\n ...\n [1303 2438]]",
        "[[ 220 2420]\n ...\n [ 219 2460]]",
        "[[1281 2434]\n ...\n [1282 2475]]",
        "[[1366 2480]\n ...\n [1368 2521]]",
        "[[ 267 2508]\n ...\n [ 265 2547]]",
        "[[1386 2517]\n ...\n [1387 2562]]"
      ],
      "vis_fonts": [
        "<paddlex.utils.fonts.Font object at 0x000001D9CA031670>",
        "<paddlex.utils.fonts.Font object at 0x000001D9CA031670>",
        "<paddlex.utils.fonts.Font object at 0x000001D9CA031670>",
        "<paddlex.utils.fonts.Font object at 0x000001D9CA031670>",
        "<paddlex.utils.fonts.Font object at 0x000001D9CA031670>",
        "<paddlex.utils.fonts.Font object at 0x000001D9CA031670>",
        "<paddlex.utils.fonts.Font object at 0x000001D9CA031670>",
        "<paddlex.utils.fonts.Font object at 0x000001D9CA031670>",
        "<paddlex.utils.fonts.Font object at 0x000001D9CA031670>",
        "<paddlex.utils.fonts.Font object at 0x000001D9CA031670>",
        "<paddlex.utils.fonts.Font object at 0x000001D9CA031670>",
        "<paddlex.utils.fonts.Font object at 0x000001D9CA031670>",
        "<paddlex.utils.fonts.Font object at 0x000001D9CA031670>",
        "<paddlex.utils.fonts.Font object at 0x000001D9CA031670>",
        "<paddlex.utils.fonts.Font object at 0x000001D9CA031670>",
        "<paddlex.utils.fonts.Font object at 0x000001D9CA031670>",
        "<paddlex.utils.fonts.Font object at 0x000001D9CA031670>",
        "<paddlex.utils.fonts.Font object at 0x000001D9CA031670>",
        "<paddlex.utils.fonts.Font object at 0x000001D9CA031670>",
        "<paddlex.utils.fonts.Font object at 0x000001D9CA031670>",
        "<paddlex.utils.fonts.Font object at 0x000001D9CA031670>",
        "<paddlex.utils.fonts.Font object at 0x000001D9CA031670>",
        "<paddlex.utils.fonts.Font object at 0x000001D9CA031670>",
        "<paddlex.utils.fonts.Font object at 0x000001D9CA031670>",
        "<paddlex.utils.fonts.Font object at 0x000001D9CA031670>",
        "<paddlex.utils.fonts.Font object at 0x000001D9CA031670>",
        "<paddlex.utils.fonts.Font object at 0x000001D9CA031670>",
        "<paddlex.utils.fonts.Font object at 0x000001D9CA031670>",
        "<paddlex.utils.fonts.Font object at 0x000001D9CA031670>",
        "<paddlex.utils.fonts.Font object at 0x000001D9CA031670>",
        "<paddlex.utils.fonts.Font object at 0x000001D9CA031670>",
        "<paddlex.utils.fonts.Font object at 0x000001D9CA031670>",
        "<paddlex.utils.fonts.Font object at 0x000001D9CA031670>",
        "<paddlex.utils.fonts.Font object at 0x000001D9CA031670>",
        "<paddlex.utils.fonts.Font object at 0x000001D9CA031670>",
        "<paddlex.utils.fonts.Font object at 0x000001D9CA031670>",
        "<paddlex.utils.fonts.Font object at 0x000001D9CA031670>",
        "<paddlex.utils.fonts.Font object at 0x000001D9CA031670>",
        "<paddlex.utils.fonts.Font object at 0x000001D9CA031670>",
        "<paddlex.utils.fonts.Font object at 0x000001D9CA031670>",
        "<paddlex.utils.fonts.Font object at 0x000001D9CA031670>",
        "<paddlex.utils.fonts.Font object at 0x000001D9CA031670>",
        "<paddlex.utils.fonts.Font object at 0x000001D9CA031670>",
        "<paddlex.utils.fonts.Font object at 0x000001D9CA031670>",
        "<paddlex.utils.fonts.Font object at 0x000001D9CA031670>",
        "<paddlex.utils.fonts.Font object at 0x000001D9CA031670>",
        "<paddlex.utils.fonts.Font object at 0x000001D9CA031670>",
        "<paddlex.utils.fonts.Font object at 0x000001D9CA031670>",
        "<paddlex.utils.fonts.Font object at 0x000001D9CA031670>",
        "<paddlex.utils.fonts.Font object at 0x000001D9CA031670>",
        "<paddlex.utils.fonts.Font object at 0x000001D9CA031670>",
        "<paddlex.utils.fonts.Font object at 0x000001D9CA031670>",
        "<paddlex.utils.fonts.Font object at 0x000001D9CA031670>",
        "<paddlex.utils.fonts.Font object at 0x000001D9CA031670>",
        "<paddlex.utils.fonts.Font object at 0x000001D9CA031670>",
        "<paddlex.utils.fonts.Font object at 0x000001D9CA031670>",
        "<paddlex.utils.fonts.Font object at 0x000001D9CA031670>",
        "<paddlex.utils.fonts.Font object at 0x000001D9CA031670>",
        "<paddlex.utils.fonts.Font object at 0x000001D9CA031670>",
        "<paddlex.utils.fonts.Font object at 0x000001D9CA031670>",
        "<paddlex.utils.fonts.Font object at 0x000001D9CA031670>",
        "<paddlex.utils.fonts.Font object at 0x000001D9CA031670>",
        "<paddlex.utils.fonts.Font object at 0x000001D9CA031670>",
        "<paddlex.utils.fonts.Font object at 0x000001D9CA031670>",
        "<paddlex.utils.fonts.Font object at 0x000001D9CA031670>",
        "<paddlex.utils.fonts.Font object at 0x000001D9CA031670>",
        "<paddlex.utils.fonts.Font object at 0x000001D9CA031670>",
        "<paddlex.utils.fonts.Font object at 0x000001D9CA031670>",
        "<paddlex.utils.fonts.Font object at 0x000001D9CA031670>",
        "<paddlex.utils.fonts.Font object at 0x000001D9CA031670>",
        "<paddlex.utils.fonts.Font object at 0x000001D9CA031670>",
        "<paddlex.utils.fonts.Font object at 0x000001D9CA031670>",
        "<paddlex.utils.fonts.Font object at 0x000001D9CA031670>",
        "<paddlex.utils.fonts.Font object at 0x000001D9CA031670>",
        "<paddlex.utils.fonts.Font object at 0x000001D9CA031670>",
        "<paddlex.utils.fonts.Font object at 0x000001D9CA031670>",
        "<paddlex.utils.fonts.Font object at 0x000001D9CA031670>",
        "<paddlex.utils.fonts.Font object at 0x000001D9CA031670>",
        "<paddlex.utils.fonts.Font object at 0x000001D9CA031670>",
        "<paddlex.utils.fonts.Font object at 0x000001D9CA031670>",
        "<paddlex.utils.fonts.Font object at 0x000001D9CA031670>",
        "<paddlex.utils.fonts.Font object at 0x000001D9CA031670>",
        "<paddlex.utils.fonts.Font object at 0x000001D9CA031670>",
        "<paddlex.utils.fonts.Font object at 0x000001D9CA031670>",
        "<paddlex.utils.fonts.Font object at 0x000001D9CA031670>",
        "<paddlex.utils.fonts.Font object at 0x000001D9CA031670>",
        "<paddlex.utils.fonts.Font object at 0x000001D9CA031670>",
        "<paddlex.utils.fonts.Font object at 0x000001D9CA031670>",
        "<paddlex.utils.fonts.Font object at 0x000001D9CA031670>",
        "<paddlex.utils.fonts.Font object at 0x000001D9CA031670>",
        "<paddlex.utils.fonts.Font object at 0x000001D9CA031670>",
        "<paddlex.utils.fonts.Font object at 0x000001D9CA031670>",
        "<paddlex.utils.fonts.Font object at 0x000001D9CA031670>",
        "<paddlex.utils.fonts.Font object at 0x000001D9CA031670>",
        "<paddlex.utils.fonts.Font object at 0x000001D9CA031670>",
        "<paddlex.utils.fonts.Font object at 0x000001D9CA031670>",
        "<paddlex.utils.fonts.Font object at 0x000001D9CA031670>",
        "<paddlex.utils.fonts.Font object at 0x000001D9CA031670>",
        "<paddlex.utils.fonts.Font object at 0x000001D9CA031670>",
        "<paddlex.utils.fonts.Font object at 0x000001D9CA031670>",
        "<paddlex.utils.fonts.Font object at 0x000001D9CA031670>",
        "<paddlex.utils.fonts.Font object at 0x000001D9CA031670>",
        "<paddlex.utils.fonts.Font object at 0x000001D9CA031670>",
        "<paddlex.utils.fonts.Font object at 0x000001D9CA031670>",
        "<paddlex.utils.fonts.Font object at 0x000001D9CA031670>",
        "<paddlex.utils.fonts.Font object at 0x000001D9CA031670>",
        "<paddlex.utils.fonts.Font object at 0x000001D9CA031670>",
        "<paddlex.utils.fonts.Font object at 0x000001D9CA031670>",
        "<paddlex.utils.fonts.Font object at 0x000001D9CA031670>",
        "<paddlex.utils.fonts.Font object at 0x000001D9CA031670>",
        "<paddlex.utils.fonts.Font object at 0x000001D9CA031670>",
        "<paddlex.utils.fonts.Font object at 0x000001D9CA031670>",
        "<paddlex.utils.fonts.Font object at 0x000001D9CA031670>",
        "<paddlex.utils.fonts.Font object at 0x000001D9CA031670>",
        "<paddlex.utils.fonts.Font object at 0x000001D9CA031670>",
        "<paddlex.utils.fonts.Font object at 0x000001D9CA031670>",
        "<paddlex.utils.fonts.Font object at 0x000001D9CA031670>",
        "<paddlex.utils.fonts.Font object at 0x000001D9CA031670>",
        "<paddlex.utils.fonts.Font object at 0x000001D9CA031670>",
        "<paddlex.utils.fonts.Font object at 0x000001D9CA031670>",
        "<paddlex.utils.fonts.Font object at 0x000001D9CA031670>",
        "<paddlex.utils.fonts.Font object at 0x000001D9CA031670>",
        "<paddlex.utils.fonts.Font object at 0x000001D9CA031670>",
        "<paddlex.utils.fonts.Font object at 0x000001D9CA031670>",
        "<paddlex.utils.fonts.Font object at 0x000001D9CA031670>",
        "<paddlex.utils.fonts.Font object at 0x000001D9CA031670>",
        "<paddlex.utils.fonts.Font object at 0x000001D9CA031670>",
        "<paddlex.utils.fonts.Font object at 0x000001D9CA031670>",
        "<paddlex.utils.fonts.Font object at 0x000001D9CA031670>",
        "<paddlex.utils.fonts.Font object at 0x000001D9CA031670>",
        "<paddlex.utils.fonts.Font object at 0x000001D9CA031670>",
        "<paddlex.utils.fonts.Font object at 0x000001D9CA031670>",
        "<paddlex.utils.fonts.Font object at 0x000001D9CA031670>"
      ],
      "textline_orientation_angles": [
        1,
        1,
        1,
        1,
        1,
        1,
        1,
        1,
        1,
        1,
        1,
        1,
        1,
        1,
        1,
        1,
        1,
        1,
        1,
        1,
        1,
        1,
        1,
        1,
        1,
        1,
        1,
        1,
        1,
        1,
        1,
        1,
        1,
        1,
        1,
        1,
        1,
        1,
        1,
        1,
        1,
        1,
        1,
        1,
        1,
        1,
        1,
        1,
        1,
        1,
        1,
        1,
        1,
        1,
        1,
        1,
        1,
        1,
        1,
        1,
        1,
        1,
        1,
        1,
        1,
        1,
        1,
        1,
        1,
        1,
        1,
        1,
        1,
        1,
        1,
        1,
        1,
        1,
        1,
        1,
        1,
        1,
        1,
        1,
        1,
        1,
        1,
        1,
        1,
        1,
        1,
        1,
        1,
        1,
        1,
        1,
        1,
        1,
        1,
        1,
        1,
        1,
        1,
        1,
        1,
        1,
        1,
        1,
        1,
        1,
        1,
        1,
        1,
        1,
        1,
        1,
        1,
        1,
        1,
        1,
        1,
        1,
        1,
        1,
        1,
        1,
        1,
        1,
        1,
        1,
        1,
        1,
        1
      ],
      "rec_boxes": "[[ 262 ...   54]\n ...\n [1386 ... 2562]]",
      "rec_labels": [
        "text",
        "text",
        "text",
        "text",
        "text",
        "text",
        "text",
        "text",
        "text",
        "text",
        "text",
        "text",
        "text",
        "text",
        "text",
        "text",
        "text",
        "text",
        "text",
        "text",
        "text",
        "text",
        "text",
        "text",
        "text",
        "text",
        "text",
        "text",
        "text",
        "text",
        "text",
        "text",
        "text",
        "text",
        "text",
        "text",
        "text",
        "text",
        "text",
        "text",
        "text",
        "text",
        "text",
        "text",
        "text",
        "text",
        "text",
        "text",
        "text",
        "text",
        "text",
        "text",
        "text",
        "text",
        "text",
        "text",
        "text",
        "text",
        "text",
        "text",
        "text",
        "text",
        "text",
        "text",
        "text",
        "text",
        "text",
        "text",
        "text",
        "text",
        "text",
        "text",
        "text",
        "text",
        "text",
        "text",
        "text",
        "text",
        "text",
        "text",
        "text",
        "text",
        "text",
        "text",
        "text",
        "text",
        "text",
        "text",
        "text",
        "text",
        "text",
        "text",
        "text",
        "text",
        "text",
        "text",
        "text",
        "text",
        "text",
        "text",
        "text",
        "text",
        "text",
        "text",
        "text",
        "text",
        "text",
        "text",
        "text",
        "text",
        "text",
        "text",
        "text",
        "text",
        "text",
        "text",
        "text",
        "text",
        "text",
        "text",
        "text",
        "text",
        "text",
        "text",
        "text",
        "text",
        "text",
        "text",
        "text",
        "text",
        "text",
        "text",
        "text"
      ]
    },
    "table_res_list": [
      {
        "cell_box_list": [
          "[1388. ... 2566.]",
          "[ 266. ... 2559.]",
          "[1368. ... 2525.]",
          "[1285. ... 2479.]",
          "[ 222. ... 2482.]",
          "[1305. ... 2444.]",
          "[ 224. ... 2440.]",
          "[1304. ... 2395.]",
          "[ 959. ... 2400.]",
          "[ 657. ... 2401.]",
          "[ 224. ... 2396.]",
          "[1386. ... 2357.]",
          "[ 224. ... 2352.]",
          "[1375. ... 2308.]",
          "[ 226. ... 2309.]",
          "[1415. ... 2267.]",
          "[1342. ... 2219.]",
          "[ 965. ... 2220.]",
          "[ 662. ... 2218.]",
          "[ 273. ... 2217.]",
          "[1299. ... 2181.]",
          "[ 276. ... 2177.]",
          "[1520. ... 2140.]",
          "[1343. ... 2096.]",
          "[ 963. ... 2093.]",
          "[ 662. ... 2094.]",
          "[ 275. ... 2092.]",
          "[1298. ... 2057.]",
          "[ 277. ... 2051.]",
          "[1494. ... 2016.]",
          "[ 274. ... 2017.]",
          "[1321. ... 1972.]",
          "[ 968. ... 1967.]",
          "[ 671. ... 1970.]",
          "[ 276. ... 1969.]",
          "[1301. ... 1933.]",
          "[ 276. ... 1927.]",
          "[1352. ... 1892.]",
          "[ 277. ... 1890.]",
          "[1385. ... 1854.]",
          "[1371. ... 1807.]",
          "[ 230. ... 1807.]",
          "[1338. ... 1763.]",
          "[ 964. ... 1759.]",
          "[ 664. ... 1762.]",
          "[ 278. ... 1760.]",
          "[1432. ... 1724.]",
          "[ 276. ... 1722.]",
          "[1337. ... 1678.]",
          "[ 962. ... 1675.]",
          "[ 665. ... 1677.]",
          "[ 278. ... 1676.]",
          "[1403. ... 1637.]",
          "[ 279. ... 1634.]",
          "[1320. ... 1591.]",
          "[ 962. ... 1590.]",
          "[ 668. ... 1592.]",
          "[ 278. ... 1591.]",
          "[1301. ... 1551.]",
          "[ 277. ... 1549.]",
          "[1349. ... 1514.]",
          "[ 278. ... 1515.]",
          "[1391. ... 1466.]",
          "[ 232. ... 1470.]",
          "[1276. ... 1417.]",
          "[ 962. ... 1417.]",
          "[ 663. ... 1421.]",
          "[ 279. ... 1421.]",
          "[1520. ... 1375.]",
          "[ 278. ... 1385.]",
          "[1273. ... 1332.]",
          "[ 961. ... 1333.]",
          "[ 663. ... 1335.]",
          "[ 278. ... 1338.]",
          "[1490. ... 1291.]",
          "[ 278. ... 1300.]",
          "[ 228. ... 1254.]",
          "[1420. ... 1242.]",
          "[1509. ... 1200.]",
          "[ 962. ... 1158.]",
          "[ 665. ... 1160.]",
          "[ 276. ... 1167.]",
          "[1385. ... 1153.]",
          "[1286. ... 1119.]",
          "[ 662. ... 1077.]",
          "[ 276. ... 1083.]",
          "[1384. ... 1070.]",
          "[ 963. ... 1072.]",
          "[1380. ... 1032.]",
          "[1486. ...  992.]",
          "[1316. ...  947.]",
          "[961. ... 946.]",
          "[664. ... 951.]",
          "[276. ... 956.]",
          "[1295. ...  910.]",
          "[276. ... 917.]",
          "[1387. ...  866.]",
          "[1466. ...  827.]",
          "[226. ... 795.]",
          "[1339. ...  780.]",
          "[226. ... 754.]",
          "[1321. ...  742.]",
          "[226. ... 714.]",
          "[226. ... 667.]",
          "[1383. ...  656.]",
          "[225. ... 625.]",
          "[274. ... 578.]",
          "[1351. ...  565.]",
          "[274. ... 542.]",
          "[1419. ...  527.]",
          "[276. ... 491.]",
          "[1350. ...  478.]",
          "[275. ... 453.]",
          "[1390. ...  442.]",
          "[274. ... 405.]",
          "[1311. ...  391.]",
          "[276. ... 364.]",
          "[1291. ...  353.]",
          "[276. ... 324.]",
          "[1354. ...  313.]",
          "[226. ... 280.]",
          "[1339. ...  268.]",
          "[273. ... 231.]",
          "[1310. ...  220.]",
          "[270. ... 192.]",
          "[1417. ...  181.]",
          "[1310. ...  137.]",
          "[270. ... 146.]",
          "[1389. ...  101.]",
          "[267. ... 108.]",
          "[1308. ...   52.]",
          "[264. ...  62.]"
        ],
        "table_ocr_pred": {
          "rec_polys": "[[[ 212   16]\n  ...\n  [ 213   58]]\n\n ...\n\n [[1186 2523]\n  ...\n  [1187 2564]]]",
          "rec_texts": [
            "efek-efek yang",
            "securities",
            "diperdagangkan",
            "Investments of policyholder",
            "Investasi pemegang polis",
            "in unit-linked contracts",
            "pada kontrak unit-linked",
            "6,910,606",
            "7,971,923",
            "Securities purchased under",
            "Efek yang dibeli dengan",
            "janji dijual kembali",
            "agreement to resale",
            "Wesel ekspor dan",
            "Bills and other receivables",
            "tagihan lainnya",
            "Wesel ekspor dan",
            "8,181,871",
            "7,087,118",
            "Bills and other",
            "tagihan lainnya pihak",
            "receivables third parties",
            "ketiga",
            "Wesel ekspor dan",
            "5,338,937",
            "6,208,736",
            "Bills and other",
            "tagihan lainnya pihak",
            "receivables related",
            "berelasi",
            "parties",
            "Cadangan kerugian",
            "67,962）",
            "52,828）",
            "Allowance for impairment",
            "penurunan nilai pada",
            "losses for bills and other",
            "wesel ekspor dan",
            "receivables",
            "tagihan lainnya",
            "Tagihan akseptasi",
            "Acceptance receivables",
            "Tagihan akseptasi",
            "13.528.919",
            "13,193,510",
            "Acceptance receivyables",
            " pihak ketiga",
            "third parties",
            "Tagihan akseptasi",
            "6,053,827",
            "2,825,260",
            "Acceptance receivables",
            "pihak berelasi",
            "related parties",
            "Cadangan kerugian",
            "133,986 )",
            "93,249 )",
            "Allowance for impairment",
            " penurunan nilai pada",
            "losses for acceptance",
            "tagihan akseptasi",
            "receivables",
            "Tagihan derivatif",
            "Derivative receivables",
            "Tagihan derivatif pihak",
            "4,654,266",
            "1,451,146",
            "Derivative receivables",
            "ketiga",
            "third parties",
            "Tagihan derivatif pihak",
            "768,083",
            "341,832",
            "Derivative receivables",
            "berelasi",
            "related parties",
            "Loans",
            "Pinjaman yang",
            "diberikan",
            "660,513,890",
            "616,469.089",
            "Loans third parties",
            "Pinjaman yang",
            "diberikan pihak ketiga",
            "239,016,801",
            "159,402,689",
            "Loans related parties",
            "Pinjaman yang",
            "diberikan pihak",
            "berelasi",
            "Cadangan kerugian",
            "( 35,860,626 )",
            "( 38,684,520 )",
            "Allowance for impairment",
            "losses for loans",
            "penurunan nilai pada",
            "pinjaman yang",
            "diberikan",
            "Receivables from clearing",
            "Piutang dari lembaga",
            "and settlement guarantee",
            "kliring dan penjaminan",
            "institution",
            "Receivables from",
            "Piutang nasabah",
            "customers",
            "Receivables from",
            "Piutang nasabah",
            "customers third parties",
            "pihak ketiga",
            "Receivables from",
            "Piutang nasabah",
            "pihak berelasi",
            "customers related parties",
            "Allowance for impairment",
            "Cadangan kerugian",
            "penurunan nilai pada",
            "losses for receivables",
            "from customers",
            "piutang nasabah",
            "Murabahah receivables",
            "Piutang murabahah",
            "Piutang murabahah",
            "Murabahah receivables",
            "pihak ketiga",
            "third parties",
            "Piutang murabahah",
            "Murabahah receivables",
            " pihak berelasi",
            "related parties",
            "Cadangan kerugian",
            "Allowance for impairment"
          ],
          "rec_scores": "[0.99462062 ... 0.96989584]",
          "rec_boxes": [
            [
              212,
              8,
              438,
              58
            ],
            [
              1412,
              15,
              1560,
              59
            ],
            [
              215,
              49,
              458,
              97
            ],
            [
              1206,
              92,
              1604,
              144
            ],
            [
              168,
              95,
              541,
              144
            ],
            [
              1275,
              134,
              1602,
              178
            ],
            [
              166,
              130,
              521,
              182
            ],
            [
              709,
              174,
              867,
              212
            ],
            [
              1018,
              173,
              1169,
              210
            ],
            [
              1204,
              178,
              1602,
              224
            ],
            [
              167,
              179,
              522,
              226
            ],
            [
              164,
              217,
              440,
              268
            ],
            [
              1308,
              222,
              1602,
              263
            ],
            [
              166,
              266,
              451,
              309
            ],
            [
              1185,
              265,
              1600,
              309
            ],
            [
              164,
              307,
              411,
              352
            ],
            [
              213,
              355,
              484,
              392
            ],
            [
              711,
              354,
              861,
              388
            ],
            [
              1018,
              356,
              1164,
              387
            ],
            [
              1341,
              357,
              1553,
              392
            ],
            [
              212,
              393,
              527,
              434
            ],
            [
              1203,
              397,
              1550,
              430
            ],
            [
              209,
              434,
              306,
              476
            ],
            [
              211,
              478,
              483,
              517
            ],
            [
              712,
              481,
              863,
              515
            ],
            [
              1015,
              480,
              1164,
              515
            ],
            [
              1338,
              482,
              1551,
              514
            ],
            [
              210,
              517,
              528,
              557
            ],
            [
              1272,
              523,
              1549,
              550
            ],
            [
              208,
              558,
              332,
              598
            ],
            [
              1443,
              557,
              1552,
              597
            ],
            [
              210,
              602,
              505,
              644
            ],
            [
              731,
              607,
              858,
              638
            ],
            [
              1036,
              604,
              1155,
              638
            ],
            [
              1182,
              605,
              1550,
              635
            ],
            [
              208,
              641,
              525,
              685
            ],
            [
              1196,
              647,
              1550,
              674
            ],
            [
              208,
              682,
              474,
              720
            ],
            [
              1378,
              684,
              1549,
              713
            ],
            [
              206,
              720,
              441,
              762
            ],
            [
              158,
              767,
              455,
              809
            ],
            [
              1226,
              767,
              1596,
              799
            ],
            [
              206,
              811,
              488,
              855
            ],
            [
              698,
              815,
              862,
              846
            ],
            [
              998,
              812,
              1162,
              846
            ],
            [
              1202,
              814,
              1548,
              844
            ],
            [
              204,
              850,
              394,
              897
            ],
            [
              1373,
              852,
              1550,
              886
            ],
            [
              205,
              896,
              489,
              940
            ],
            [
              714,
              899,
              864,
              931
            ],
            [
              1013,
              897,
              1161,
              931
            ],
            [
              1201,
              898,
              1548,
              931
            ],
            [
              206,
              937,
              423,
              981
            ],
            [
              1337,
              940,
              1547,
              968
            ],
            [
              206,
              983,
              506,
              1026
            ],
            [
              716,
              984,
              864,
              1017
            ],
            [
              1033,
              982,
              1158,
              1017
            ],
            [
              1180,
              983,
              1548,
              1015
            ],
            [
              206,
              1023,
              525,
              1066
            ],
            [
              1230,
              1025,
              1549,
              1055
            ],
            [
              205,
              1060,
              477,
              1104
            ],
            [
              1376,
              1059,
              1548,
              1091
            ],
            [
              156,
              1108,
              435,
              1153
            ],
            [
              1249,
              1104,
              1594,
              1139
            ],
            [
              207,
              1157,
              550,
              1197
            ],
            [
              718,
              1157,
              864,
              1188
            ],
            [
              1019,
              1153,
              1163,
              1189
            ],
            [
              1226,
              1153,
              1547,
              1186
            ],
            [
              205,
              1199,
              306,
              1240
            ],
            [
              1372,
              1189,
              1548,
              1224
            ],
            [
              206,
              1242,
              553,
              1285
            ],
            [
              744,
              1241,
              865,
              1273
            ],
            [
              1040,
              1239,
              1163,
              1273
            ],
            [
              1226,
              1236,
              1548,
              1272
            ],
            [
              207,
              1283,
              336,
              1323
            ],
            [
              1336,
              1274,
              1548,
              1310
            ],
            [
              1496,
              1320,
              1598,
              1356
            ],
            [
              160,
              1332,
              406,
              1375
            ],
            [
              160,
              1374,
              317,
              1412
            ],
            [
              681,
              1416,
              864,
              1447
            ],
            [
              982,
              1414,
              1161,
              1445
            ],
            [
              1274,
              1407,
              1550,
              1443
            ],
            [
              211,
              1421,
              441,
              1457
            ],
            [
              212,
              1455,
              540,
              1496
            ],
            [
              679,
              1502,
              863,
              1533
            ],
            [
              981,
              1497,
              1164,
              1533
            ],
            [
              1239,
              1491,
              1550,
              1531
            ],
            [
              212,
              1504,
              442,
              1543
            ],
            [
              213,
              1542,
              446,
              1581
            ],
            [
              212,
              1582,
              340,
              1621
            ],
            [
              216,
              1627,
              510,
              1668
            ],
            [
              658,
              1628,
              865,
              1662
            ],
            [
              964,
              1623,
              1162,
              1660
            ],
            [
              1182,
              1618,
              1550,
              1656
            ],
            [
              1318,
              1657,
              1550,
              1693
            ],
            [
              215,
              1664,
              531,
              1708
            ],
            [
              216,
              1708,
              439,
              1747
            ],
            [
              218,
              1747,
              360,
              1782
            ],
            [
              1219,
              1779,
              1600,
              1822
            ],
            [
              173,
              1794,
              487,
              1830
            ],
            [
              1224,
              1820,
              1600,
              1861
            ],
            [
              175,
              1832,
              505,
              1869
            ],
            [
              1456,
              1860,
              1600,
              1897
            ],
            [
              1325,
              1907,
              1600,
              1944
            ],
            [
              175,
              1918,
              443,
              1960
            ],
            [
              1430,
              1949,
              1601,
              1984
            ],
            [
              1296,
              1996,
              1552,
              2030
            ],
            [
              226,
              2009,
              475,
              2043
            ],
            [
              1218,
              2032,
              1552,
              2074
            ],
            [
              225,
              2047,
              407,
              2084
            ],
            [
              1295,
              2083,
              1550,
              2118
            ],
            [
              227,
              2096,
              476,
              2131
            ],
            [
              226,
              2132,
              436,
              2172
            ],
            [
              1184,
              2121,
              1551,
              2163
            ],
            [
              1184,
              2169,
              1552,
              2210
            ],
            [
              228,
              2183,
              515,
              2217
            ],
            [
              226,
              2221,
              535,
              2257
            ],
            [
              1235,
              2210,
              1550,
              2247
            ],
            [
              1322,
              2250,
              1550,
              2286
            ],
            [
              228,
              2261,
              472,
              2298
            ],
            [
              1237,
              2294,
              1600,
              2339
            ],
            [
              179,
              2306,
              487,
              2346
            ],
            [
              226,
              2354,
              516,
              2393
            ],
            [
              1213,
              2343,
              1553,
              2387
            ],
            [
              223,
              2393,
              409,
              2434
            ],
            [
              1376,
              2382,
              1556,
              2424
            ],
            [
              223,
              2437,
              516,
              2478
            ],
            [
              1213,
              2428,
              1556,
              2473
            ],
            [
              220,
              2473,
              437,
              2520
            ],
            [
              1343,
              2466,
              1559,
              2511
            ],
            [
              221,
              2522,
              518,
              2568
            ],
            [
              1186,
              2512,
              1562,
              2564
            ]
          ]
        },
        "pred_html": "<html><body><table><tbody><tr><td>efek-efek yang</td><td>securities</td><td>diperdagangkan</td><td></td></tr><tr><td>Investasi pemegang polis</td><td>Investments of policyholder</td><td>pada kontrak unit-linked</td><td>in unit-linked contracts</td></tr><tr><td>Efek yang dibeli dengan</td><td>6,910,606</td><td>7,971,923</td><td>Securities purchased under</td></tr><tr><td>janji dijual kembali</td><td>agreement to resale</td><td>Wesel ekspor dan</td><td>Bills and other receivables</td></tr><tr><td>Wesel ekspor dan</td><td>8,181,871</td><td>7,087,118</td><td>Bills and other</td></tr><tr><td>tagihan lainnya pihak</td><td>receivables third parties</td><td>ketiga</td><td></td></tr><tr><td>Wesel ekspor dan</td><td>5,338,937</td><td>6,208,736</td><td>Bills and other</td></tr><tr><td>tagihan lainnya pihak</td><td>receivables related</td><td>berelasi</td><td>parties</td></tr><tr><td>Cadangan kerugian</td><td>67,962）</td><td>52,828）</td><td>Allowance for impairment</td></tr><tr><td>penurunan nilai pada</td><td>losses for bills and other</td><td>wesel ekspor dan</td><td>receivables</td></tr><tr><td>Tagihan akseptasi</td><td>Acceptance receivables</td><td></td><td></td></tr><tr><td>Tagihan akseptasi</td><td>13.528.919</td><td>13,193,510</td><td>Acceptance receivyables</td></tr><tr><td>Tagihan akseptasi</td><td>6,053,827</td><td>2,825,260</td><td>Acceptance receivables</td></tr><tr><td>pihak berelasi</td><td>related parties</td><td></td><td></td></tr><tr><td>Cadangan kerugian</td><td>133,986 )</td><td>93,249 )</td><td>Allowance for impairment</td></tr><tr><td>tagihan akseptasi</td><td>receivables</td><td>Tagihan derivatif</td><td>Derivative receivables</td></tr><tr><td>Tagihan derivatif pihak</td><td>4,654,266</td><td>1,451,146</td><td>Derivative receivables</td></tr><tr><td>ketiga</td><td>third parties</td><td></td><td></td></tr><tr><td>Tagihan derivatif pihak</td><td>768,083</td><td>341,832</td><td>Derivative receivables</td></tr><tr><td>Loans</td><td>Pinjaman yang</td><td>diberikan</td><td></td></tr><tr><td>660,513,890</td><td>616,469.089</td><td>Loans third parties</td><td>Pinjaman yang</td></tr><tr><td>159,402,689</td><td>Loans related parties</td><td>Pinjaman yang</td><td>239,016,801</td></tr><tr><td>diberikan pihak</td><td>berelasi</td><td></td><td></td></tr><tr><td>Cadangan kerugian</td><td>( 35,860,626 )</td><td>( 38,684,520 )</td><td>Allowance for impairment</td></tr><tr><td>pinjaman yang</td><td>diberikan</td><td>Receivables from clearing</td><td>Piutang dari lembaga</td></tr><tr><td>and settlement guarantee</td><td>kliring dan penjaminan</td><td>institution</td><td>Receivables from</td></tr><tr><td>Piutang nasabah</td><td>customers</td><td>Receivables from</td><td>Piutang nasabah</td></tr><tr><td>customers third parties</td><td>pihak ketiga</td><td>Receivables from</td><td>Piutang nasabah</td></tr><tr><td>customers related parties</td><td>pihak berelasi</td><td>Allowance for impairment</td><td>Cadangan kerugian</td></tr><tr><td>losses for receivables</td><td>penurunan nilai pada</td><td>from customers</td><td>piutang nasabah</td></tr><tr><td>Murabahah receivables</td><td>Piutang murabahah</td><td>Murabahah receivables</td><td>Piutang murabahah</td></tr><tr><td>third parties</td><td>pihak ketiga</td><td>Piutang murabahah</td><td>Murabahah receivables</td></tr><tr><td> pihak berelasi</td><td>related parties</td><td>Cadangan kerugian</td><td>Allowance for impairment</td></tr><tr><td></td><td></td><td></td><td></td></tr><tr><td></td><td></td><td></td><td></td></tr><tr><td></td><td></td><td></td><td></td></tr><tr><td></td><td></td><td></td><td></td></tr><tr><td></td><td></td><td></td><td></td></tr><tr><td></td><td></td><td></td><td></td></tr><tr><td></td><td></td><td></td><td></td></tr><tr><td></td><td></td><td></td><td></td></tr><tr><td></td><td></td><td></td><td></td></tr><tr><td></td><td></td><td></td><td></td></tr><tr><td></td><td></td><td></td><td></td></tr><tr><td></td><td></td><td></td><td></td></tr><tr><td></td><td></td><td></td><td></td></tr><tr><td></td><td></td><td></td><td></td></tr><tr><td></td><td></td><td></td><td></td></tr><tr><td></td><td></td><td></td><td></td></tr><tr><td></td><td></td><td></td><td></td></tr><tr><td></td><td></td><td></td><td></td></tr><tr><td></td><td></td><td></td><td></td></tr><tr><td></td><td></td><td></td><td></td></tr><tr><td></td><td></td><td></td><td></td></tr><tr><td></td><td></td><td></td><td></td></tr><tr><td></td><td></td><td></td><td></td></tr><tr><td></td><td></td><td></td><td></td></tr><tr><td></td><td></td><td></td><td></td></tr><tr><td></td><td></td><td></td><td></td></tr><tr><td></td><td></td><td></td><td></td></tr><tr><td></td><td></td><td></td><td></td></tr><tr><td></td><td></td><td></td><td></td></tr><tr><td></td><td></td><td></td><td></td></tr><tr><td></td><td></td><td></td><td></td></tr><tr><td></td><td></td><td></td><td></td></tr><tr><td></td><td></td><td></td><td></td></tr><tr><td></td><td></td><td></td><td></td></tr><tr><td></td><td></td><td></td><td></td></tr><tr><td></td><td></td><td></td><td></td></tr><tr><td></td><td></td><td></td><td></td></tr><tr><td></td><td></td><td></td><td></td></tr><tr><td></td><td></td><td></td><td></td></tr><tr><td></td><td></td><td></td><td></td></tr><tr><td></td><td></td><td></td><td></td></tr><tr><td></td><td></td><td></td><td></td></tr><tr><td></td><td></td><td></td><td></td></tr><tr><td></td><td></td><td></td><td></td></tr><tr><td></td><td></td><td></td><td></td></tr><tr><td></td><td></td><td></td><td></td></tr><tr><td></td><td></td><td></td><td></td></tr><tr><td></td><td></td><td></td><td></td></tr><tr><td></td><td></td><td></td><td></td></tr><tr><td></td><td></td><td></td><td></td></tr><tr><td></td></table></body></html>",
        "neighbor_texts": "",
        "table_region_id": 1
      }
    ],
    "seal_res_list": [],
    "chart_res_list": [],
    "formula_res_list": [],
    "parsing_res_list": [
      "\n\n#################\nindex:\t0\nlabel:\ttable\nregion_label:\tvision\nbbox:\t[131, 0, 1741, 2570]\ncontent:\t<html><body><table><tbody><tr><td>efek-efek yang</td><td>securities</td><td>diperdagangkan</td><td></td></tr><tr><td>Investasi pemegang polis</td><td>Investments of policyholder</td><td>pada kontrak unit-linked</td><td>in unit-linked contracts</td></tr><tr><td>Efek yang dibeli dengan</td><td>6,910,606</td><td>7,971,923</td><td>Securities purchased under</td></tr><tr><td>janji dijual kembali</td><td>agreement to resale</td><td>Wesel ekspor dan</td><td>Bills and other receivables</td></tr><tr><td>Wesel ekspor dan</td><td>8,181,871</td><td>7,087,118</td><td>Bills and other</td></tr><tr><td>tagihan lainnya pihak</td><td>receivables third parties</td><td>ketiga</td><td></td></tr><tr><td>Wesel ekspor dan</td><td>5,338,937</td><td>6,208,736</td><td>Bills and other</td></tr><tr><td>tagihan lainnya pihak</td><td>receivables related</td><td>berelasi</td><td>parties</td></tr><tr><td>Cadangan kerugian</td><td>67,962）</td><td>52,828）</td><td>Allowance for impairment</td></tr><tr><td>penurunan nilai pada</td><td>losses for bills and other</td><td>wesel ekspor dan</td><td>receivables</td></tr><tr><td>Tagihan akseptasi</td><td>Acceptance receivables</td><td></td><td></td></tr><tr><td>Tagihan akseptasi</td><td>13.528.919</td><td>13,193,510</td><td>Acceptance receivyables</td></tr><tr><td>Tagihan akseptasi</td><td>6,053,827</td><td>2,825,260</td><td>Acceptance receivables</td></tr><tr><td>pihak berelasi</td><td>related parties</td><td></td><td></td></tr><tr><td>Cadangan kerugian</td><td>133,986 )</td><td>93,249 )</td><td>Allowance for impairment</td></tr><tr><td>tagihan akseptasi</td><td>receivables</td><td>Tagihan derivatif</td><td>Derivative receivables</td></tr><tr><td>Tagihan derivatif pihak</td><td>4,654,266</td><td>1,451,146</td><td>Derivative receivables</td></tr><tr><td>ketiga</td><td>third parties</td><td></td><td></td></tr><tr><td>Tagihan derivatif pihak</td><td>768,083</td><td>341,832</td><td>Derivative receivables</td></tr><tr><td>Loans</td><td>Pinjaman yang</td><td>diberikan</td><td></td></tr><tr><td>660,513,890</td><td>616,469.089</td><td>Loans third parties</td><td>Pinjaman yang</td></tr><tr><td>159,402,689</td><td>Loans related parties</td><td>Pinjaman yang</td><td>239,016,801</td></tr><tr><td>diberikan pihak</td><td>berelasi</td><td></td><td></td></tr><tr><td>Cadangan kerugian</td><td>( 35,860,626 )</td><td>( 38,684,520 )</td><td>Allowance for impairment</td></tr><tr><td>pinjaman yang</td><td>diberikan</td><td>Receivables from clearing</td><td>Piutang dari lembaga</td></tr><tr><td>and settlement guarantee</td><td>kliring dan penjaminan</td><td>institution</td><td>Receivables from</td></tr><tr><td>Piutang nasabah</td><td>customers</td><td>Receivables from</td><td>Piutang nasabah</td></tr><tr><td>customers third parties</td><td>pihak ketiga</td><td>Receivables from</td><td>Piutang nasabah</td></tr><tr><td>customers related parties</td><td>pihak berelasi</td><td>Allowance for impairment</td><td>Cadangan kerugian</td></tr><tr><td>losses for receivables</td><td>penurunan nilai pada</td><td>from customers</td><td>piutang nasabah</td></tr><tr><td>Murabahah receivables</td><td>Piutang murabahah</td><td>Murabahah receivables</td><td>Piutang murabahah</td></tr><tr><td>third parties</td><td>pihak ketiga</td><td>Piutang murabahah</td><td>Murabahah receivables</td></tr><tr><td> pihak berelasi</td><td>related parties</td><td>Cadangan kerugian</td><td>Allowance for impairment</td></tr><tr><td></td><td></td><td></td><td></td></tr><tr><td></td><td></td><td></td><td></td></tr><tr><td></td><td></td><td></td><td></td></tr><tr><td></td><td></td><td></td><td></td></tr><tr><td></td><td></td><td></td><td></td></tr><tr><td></td><td></td><td></td><td></td></tr><tr><td></td><td></td><td></td><td></td></tr><tr><td></td><td></td><td></td><td></td></tr><tr><td></td><td></td><td></td><td></td></tr><tr><td></td><td></td><td></td><td></td></tr><tr><td></td><td></td><td></td><td></td></tr><tr><td></td><td></td><td></td><td></td></tr><tr><td></td><td></td><td></td><td></td></tr><tr><td></td><td></td><td></td><td></td></tr><tr><td></td><td></td><td></td><td></td></tr><tr><td></td><td></td><td></td><td></td></tr><tr><td></td><td></td><td></td><td></td></tr><tr><td></td><td></td><td></td><td></td></tr><tr><td></td><td></td><td></td><td></td></tr><tr><td></td><td></td><td></td><td></td></tr><tr><td></td><td></td><td></td><td></td></tr><tr><td></td><td></td><td></td><td></td></tr><tr><td></td><td></td><td></td><td></td></tr><tr><td></td><td></td><td></td><td></td></tr><tr><td></td><td></td><td></td><td></td></tr><tr><td></td><td></td><td></td><td></td></tr><tr><td></td><td></td><td></td><td></td></tr><tr><td></td><td></td><td></td><td></td></tr><tr><td></td><td></td><td></td><td></td></tr><tr><td></td><td></td><td></td><td></td></tr><tr><td></td><td></td><td></td><td></td></tr><tr><td></td><td></td><td></td><td></td></tr><tr><td></td><td></td><td></td><td></td></tr><tr><td></td><td></td><td></td><td></td></tr><tr><td></td><td></td><td></td><td></td></tr><tr><td></td><td></td><td></td><td></td></tr><tr><td></td><td></td><td></td><td></td></tr><tr><td></td><td></td><td></td><td></td></tr><tr><td></td><td></td><td></td><td></td></tr><tr><td></td><td></td><td></td><td></td></tr><tr><td></td><td></td><td></td><td></td></tr><tr><td></td><td></td><td></td><td></td></tr><tr><td></td><td></td><td></td><td></td></tr><tr><td></td><td></td><td></td><td></td></tr><tr><td></td><td></td><td></td><td></td></tr><tr><td></td><td></td><td></td><td></td></tr><tr><td></td><td></td><td></td><td></td></tr><tr><td></td><td></td><td></td><td></td></tr><tr><td></td><td></td><td></td><td></td></tr><tr><td></td><td></td><td></td><td></td></tr><tr><td></td></table></body></html>\n#################"
    ],
    "imgs_in_doc": [],
    "model_settings": {
      "use_doc_preprocessor": true,
      "use_seal_recognition": false,
      "use_table_recognition": true,
      "use_formula_recognition": true,
      "use_chart_recognition": false,
      "use_region_detection": true,
      "format_block_content": false,
      "markdown_ignore_labels": [
        "number",
        "footnote",
        "header",
        "header_image",
        "footer",
        "footer_image",
        "aside_text"
      ]
    }
  }
]